dash_carbon_components/Button.py
dash_carbon_components/Card.py
dash_carbon_components/Checkbox.py
dash_carbon_components/Column.py
dash_carbon_components/DashCarbonComponents.py
dash_carbon_components/DataTable.py
dash_carbon_components/DatePicker.py
dash_carbon_components/DatePickerInput.py
dash_carbon_components/DatePickerRange.py
dash_carbon_components/Dropdown.py
dash_carbon_components/GlobalTheme.py
dash_carbon_components/Grid.py
dash_carbon_components/Link.py
dash_carbon_components/Modal.py
dash_carbon_components/MultiSelect.py
dash_carbon_components/MultiSelectFilterable.py
dash_carbon_components/NumberInput.py
dash_carbon_components/RadioButtonGroup.py
dash_carbon_components/Row.py
dash_carbon_components/Slider.py
dash_carbon_components/Tab.py
dash_carbon_components/Tabs.py
dash_carbon_components/TextInput.py
dash_carbon_components/Theme.py
dash_carbon_components/UIPage.py
dash_carbon_components/UIShell.py
dash_carbon_components/__init__.py
dash_carbon_components/_imports_.py
dash_carbon_components/dash_carbon_components.min.js
dash_carbon_components/dash_carbon_components.min.js.map
dash_carbon_components/metadata.json
dash_carbon_components/package-info.json
dash_carbon_components-0.4.3.1.dist-info/LICENSE
dash_carbon_components-0.4.3.1.dist-info/METADATA
dash_carbon_components-0.4.3.1.dist-info/WHEEL
dash_carbon_components-0.4.3.1.dist-info/top_level.txt
dash_carbon_components-0.4.3.1.dist-info/RECORD
