Metadata-Version: 2.1
Name: dash-carbon-components
Version: 0.4.3.1
Summary: Dash Components using IBM's Carbon Design System https://github.com/carbon-design-system
Author: Matheus Rangel <matheus.rangel@ibm.com>
License: Apache License Version 2.0
Project-URL: Source Code, https://github.com/Matheus-Rangel/dash-carbon-components
Classifier: Framework :: Dash
License-File: LICENSE
